ai_cachekit/__init__.py
ai_cachekit/cache.py
ai_cachekit/backends/__init__.py
ai_cachekit/backends/file_backend.py
ai_cachekit/backends/memory_backend.py
ai_cachekit/backends/redis_backend.py
ai_cachekit-1.0.0.dist-info/licenses/LICENSE
ai_cachekit-1.0.0.dist-info/METADATA
ai_cachekit-1.0.0.dist-info/WHEEL
ai_cachekit-1.0.0.dist-info/top_level.txt
ai_cachekit-1.0.0.dist-info/RECORD
