Metadata-Version: 2.4
Name: ai-cachekit
Version: 1.0.0
Summary: Universal caching system for AI responses with support for memory, file (JSON), and Redis backends.
Author: Eugen D
Author-email: Eugen D <dascaleugen@gmail.com>
License: MIT
Project-URL: Homepage, https://github.com/EDLadder/ai-cachekit
Project-URL: Repository, https://github.com/EDLadder/ai-cachekit
Keywords: cache,redis,ai,memory,file,sqlite
Classifier: Programming Language :: Python :: 3
Classifier: License :: OSI Approved :: MIT License
Classifier: Operating System :: OS Independent
Requires-Python: >=3.8
License-File: LICENSE
Requires-Dist: redis>=5.0.0
Dynamic: author
Dynamic: license-file
Dynamic: requires-python
